[{"id":"a5bd701b.d432a","type":"tab","label":"Flow 1","disabled":false,"info":""},{"id":"2bf6f4d8.b6525c","type":"mqtt in","z":"a5bd701b.d432a","name":"","topic":"+/devices/sodaq-temperature-sensor/up","qos":"2","datatype":"json","broker":"64f29cd5.966844","x":270,"y":180,"wires":[["a1b20336.8da99","235de5cb.d6cf9a","d5ac18df.2b9768"]]},{"id":"a1b20336.8da99","type":"debug","z":"a5bd701b.d432a","name":"","active":true,"tosidebar":true,"console":false,"tostatus":false,"complete":"false","x":550,"y":180,"wires":[]},{"id":"235de5cb.d6cf9a","type":"function","z":"a5bd701b.d432a","name":"Filter temperatuur","func":"msg.payload = msg.payload.payload_fields.temperature;\nreturn msg;","outputs":1,"noerr":0,"x":590,"y":240,"wires":[["d8b599a1.4a0c48","8735f70.0d90108","4783a7fd.1a3088"]]},{"id":"d8b599a1.4a0c48","type":"debug","z":"a5bd701b.d432a","name":"","active":true,"tosidebar":true,"console":false,"tostatus":false,"complete":"false","x":870,"y":240,"wires":[]},{"id":"d5ac18df.2b9768","type":"function","z":"a5bd701b.d432a","name":"Filter batterij","func":"msg.payload = msg.payload.payload_fields.battery;\nreturn msg;","outputs":1,"noerr":0,"x":550,"y":300,"wires":[["be3eb1c.0c9905","bddeff1f.8df23","9e85e045.7bd75"]]},{"id":"be3eb1c.0c9905","type":"debug","z":"a5bd701b.d432a","name":"","active":true,"tosidebar":true,"console":false,"tostatus":false,"complete":"false","x":870,"y":300,"wires":[]},{"id":"a1f031af.cdaf4","type":"ui_button","z":"a5bd701b.d432a","name":"","group":"e1c4d3aa.c0688","order":0,"width":0,"height":0,"passthru":false,"label":"Genereer Fake Temperatuur","tooltip":"","color":"","bgcolor":"","icon":"","payload":"21.5","payloadType":"num","topic":"","x":420,"y":440,"wires":[["8735f70.0d90108","4783a7fd.1a3088"]]},{"id":"8735f70.0d90108","type":"ui_gauge","z":"a5bd701b.d432a","name":"","group":"e1c4d3aa.c0688","order":1,"width":0,"height":0,"gtype":"gage","title":"Batterij Temperatuur","label":"°C","format":"{{value}}","min":"-20","max":"70","colors":["#00b500","#e6e600","#ca3838"],"seg1":"","seg2":"","x":860,"y":440,"wires":[]},{"id":"4783a7fd.1a3088","type":"ui_chart","z":"a5bd701b.d432a","name":"","group":"e1c4d3aa.c0688","order":2,"width":0,"height":0,"label":"Temperatuur Historiek","chartType":"line","legend":"false","xformat":"HH:mm:ss","interpolate":"linear","nodata":"","dot":false,"ymin":"-20","ymax":"+70","removeOlder":"12","removeOlderPoints":"","removeOlderUnit":"3600","cutout":0,"useOneColor":false,"colors":["#1f77b4","#aec7e8","#ff7f0e","#2ca02c","#98df8a","#d62728","#ff9896","#9467bd","#c5b0d5"],"useOldStyle":false,"outputs":1,"x":860,"y":500,"wires":[[]]},{"id":"9ccf8b64.3b2f48","type":"ui_slider","z":"a5bd701b.d432a","name":"","label":"Genereer Fake Percentage","tooltip":"","group":"446b82a1.9b313c","order":0,"width":0,"height":0,"passthru":true,"outs":"end","topic":"","min":0,"max":"100","step":"5","x":420,"y":560,"wires":[["bddeff1f.8df23","9e85e045.7bd75"]]},{"id":"bddeff1f.8df23","type":"ui_gauge","z":"a5bd701b.d432a","name":"","group":"446b82a1.9b313c","order":1,"width":0,"height":0,"gtype":"gage","title":"Percentage","label":"%","format":"{{value}}","min":0,"max":"100","colors":["#b51b00","#e6e600","#3eca38"],"seg1":"","seg2":"","x":840,"y":560,"wires":[]},{"id":"9e85e045.7bd75","type":"ui_chart","z":"a5bd701b.d432a","name":"","group":"446b82a1.9b313c","order":2,"width":0,"height":0,"label":"Batterij Historiek","chartType":"line","legend":"false","xformat":"HH:mm:ss","interpolate":"linear","nodata":"","dot":false,"ymin":"0","ymax":"100","removeOlder":"12","removeOlderPoints":"","removeOlderUnit":"3600","cutout":0,"useOneColor":false,"colors":["#dadf11","#aec7e8","#ff7f0e","#2ca02c","#98df8a","#d62728","#ff9896","#9467bd","#c5b0d5"],"useOldStyle":false,"outputs":1,"x":850,"y":620,"wires":[[]]},{"id":"64f29cd5.966844","type":"mqtt-broker","z":"","name":"TTN-vehicle-battery-monitor","broker":"eu.thethings.network","port":"1883","clientid":"","usetls":false,"compatmode":false,"keepalive":"60","cleansession":true,"birthTopic":"","birthQos":"0","birthPayload":"","closeTopic":"","closeQos":"0","closePayload":"","willTopic":"","willQos":"0","willPayload":""},{"id":"e1c4d3aa.c0688","type":"ui_group","z":"","name":"Temperatuur","tab":"42c49f53.61657","disp":true,"width":"6","collapse":false},{"id":"446b82a1.9b313c","type":"ui_group","z":"","name":"Batterij Spanning","tab":"42c49f53.61657","disp":true,"width":"6","collapse":false},{"id":"42c49f53.61657","type":"ui_tab","z":"","name":"Vehicle Battery Monitor","icon":"dashboard","disabled":false,"hidden":false}]